README.md
setup.py
debug_a/__init__.py
debug_a/cli.py
debug_a/cli_fire.py
debug_a/constitution.py
debug_a/labels.py
debug_a/live_or_die.py
debug_a/rest_api.py
debug_a/sms.py
debug_a/utils.py
debug_a.egg-info/PKG-INFO
debug_a.egg-info/SOURCES.txt
debug_a.egg-info/dependency_links.txt
debug_a.egg-info/entry_points.txt
debug_a.egg-info/requires.txt
debug_a.egg-info/top_level.txt
debug_a/analyst/__init__.py
debug_a/analyst/gtja.py
debug_a/analyst/pazq.py
debug_a/collector/__init__.py
debug_a/collector/base_info.py
debug_a/collector/hist.py
debug_a/collector/index.py
debug_a/collector/realtime.py
debug_a/model/__init__.py
debug_a/model/knn.py
debug_a/model/likeness.py
debug_a/monitor/__init__.py
debug_a/monitor/after_close.py
debug_a/monitor/env_monitor.py
debug_a/monitor/multi_monitor.py
debug_a/monitor/single_monitor.py
debug_a/selector/__init__.py
debug_a/selector/average_line.py
debug_a/selector/filters.py
debug_a/selector/market_capitalization.py
debug_a/selector/trades.py
debug_a/selector/utils.py
debug_a/selector/wave.py
debug_a/tools/__init__.py
debug_a/tools/file_op.py
debug_a/trader/__init__.py
debug_a/trader/account.py
debug_a/trader/pool.py
debug_a/trader/signal.py
debug_a/xueqiu/__init__.py
debug_a/xueqiu/comment.py
debug_a/xueqiu/portfolio.py
debug_a/xueqiu/screener.py
debug_a/xueqiu/utils.py
test/test_cmd.py
test/test_stock_pool.py