Metadata-Version: 1.2
Name: debug-a
Version: 0.0.2
Summary: A股盯盘机器人
Home-page: https://github.com/zengbin93/Debug_A
Author: zengbin93
Author-email: zeng_bin93@163.com
License: MIT Licence
Keywords: debug_a,robot,A股,盯盘
Platform: UNKNOWN
Requires-Python: >=3
